azhelloworldpackage/__init__.py
azhelloworldpackage-0.1.dist-info/LICENSE
azhelloworldpackage-0.1.dist-info/METADATA
azhelloworldpackage-0.1.dist-info/WHEEL
azhelloworldpackage-0.1.dist-info/top_level.txt
azhelloworldpackage-0.1.dist-info/RECORD
