Metadata-Version: 2.1
Name: azhelloworldpackage
Version: 0.1
Summary: hello world!
Home-page: https://github.com/Azadehkhojandi/helloworld
Author: Azadeh Khojandi
Author-email: azadehkhojandi@gmail.com
License: MIT
Platform: UNKNOWN
